{"layout":{"sections":[{"contents":[{"type":"block","name":"mainnav","col":12,"xl":"","lg":12,"md":12,"sm":"auto","xs":"none","hidden_lg":"","hidden_xl":"","hidden_md":"","hidden_sm":"","hidden_xs":"","style":null,"extra_class":"","extra_params":"","element":null,"block":"mainnav","positions":"","module":null,"device":"def","idx":0}],"opacity":0.5,"file_ogg":"","file_webm":"","file_mp4":"","file_cover":"","video_id":"","video_type":null,"background_position":null,"background_attachment":null,"background_size":null,"background_repeat":null,"background_image":"","overlay_type":"","color_pattern":"mainnav","sticky":"","extra_class":"","margin":"","padding":"","cols":1,"container":"none","name":"Header","margin_xs":"","margin_sm":"","margin_md":"","margin_lg":"","margin_xl":"","padding_xs":"","padding_sm":"","padding_md":"","padding_lg":"","padding_xl":"","type":"row","layout":12,"sectionid":1},{"contents":[{"type":"positions","name":"masthead","col":12,"xl":"","lg":"","md":"","sm":"","xs":"","hidden_lg":"","hidden_xl":"","hidden_md":"","hidden_sm":"","hidden_xs":"","style":"JAxhtml","extra_class":"text-center","extra_params":"","device":"def","module":null,"positions":"masthead","block":null,"element":"masthead","idx":0}],"opacity":0.5,"file_ogg":"","file_webm":"","file_mp4":"","file_cover":"","video_id":"","video_type":null,"background_position":null,"background_attachment":null,"background_size":null,"background_repeat":null,"background_image":"","overlay_type":"","color_pattern":"","sticky":"","extra_class":"","margin":"","padding":"","cols":1,"container":"none","name":"Masthead","margin_xs":"","margin_sm":"","margin_md":"","margin_lg":"","margin_xl":"","padding_xs":"","padding_sm":"","padding_md":"","padding_lg":"","padding_xl":"","type":"row","layout":12,"sectionid":1},{"contents":[{"type":"component","name":"","col":"auto","xl":"","lg":"","md":12,"sm":"","xs":12,"hidden_lg":"","hidden_xl":"","hidden_md":"","hidden_sm":"","hidden_xs":"","style":"","extra_class":"","extra_params":"","device":"md","idx":0},{"type":"positions","name":"sidebar-r","col":3,"xl":"","lg":"","md":12,"sm":"","xs":12,"hidden_lg":"","hidden_xl":"","hidden_md":"","hidden_sm":"","hidden_xs":"","style":"JAxhtml","extra_class":"","extra_params":"","element":"","block":"","positions":"sidebar-r","module":"","device":"md","idx":1}],"opacity":0.5,"file_ogg":"","file_webm":"","file_mp4":"","file_cover":"","video_id":"","video_type":null,"background_position":null,"background_attachment":null,"background_size":null,"background_repeat":null,"background_image":"","overlay_type":"","color_pattern":"","sticky":"","extra_class":"","margin":"","padding":"","cols":3,"container":1,"name":"Main body","margin_xs":"","margin_sm":"","margin_md":"","margin_lg":"","margin_xl":"","padding_xs":"","padding_sm":"","padding_md":"","padding_lg":"","padding_xl":"","type":"row","layout":"auto+3","widths":"3+6+3"},{"contents":[{"type":"positions","name":"section-8","col":6,"xl":"","lg":12,"md":12,"sm":12,"xs":12,"hidden_lg":"","hidden_xl":"","hidden_md":"","hidden_sm":"","hidden_xs":"","style":"t4section","extra_class":"","extra_params":"","device":"xs","module":null,"positions":"section-8","block":null,"element":null,"idx":0},{"type":"positions","name":"section-9","col":6,"xl":"","lg":12,"md":12,"sm":12,"xs":12,"hidden_lg":"","hidden_xl":"","hidden_md":"","hidden_sm":"","hidden_xs":"","style":"t4section","extra_class":"","extra_params":"","module":null,"positions":"section-9","block":null,"element":null,"device":"xs","idx":1}],"sectionid":1,"layout":"6+6","padding_xl":"","padding_lg":"","padding_md":"","padding_sm":"","padding_xs":"","margin_xl":"","margin_lg":"","margin_md":"","margin_sm":"","margin_xs":"","name":"spotlight-1","container":"","cols":"2","padding":"","margin":"","extra_class":"","sticky":"","color_pattern":"purple","overlay_type":"","background_image":"","background_repeat":null,"background_size":null,"background_attachment":null,"background_position":null,"video_type":null,"video_id":"","file_cover":"","file_mp4":"","file_webm":"","file_ogg":"","opacity":"0.5"},{"contents":[{"type":"positions","name":"footnav-1","col":4,"xl":"","lg":12,"md":12,"sm":12,"xs":12,"hidden_lg":"","hidden_xl":"","hidden_md":"","hidden_sm":"","hidden_xs":"","style":"JAxhtml","extra_class":"","extra_params":"","title":"Breadcrumbs","modname":"mod_breadcrumbs","module":"","positions":"footnav-1","block":"","element":"","device":"def","idx":0},{"type":"positions","name":"footnav-2","col":2,"xl":"","lg":3,"md":3,"sm":6,"xs":12,"hidden_lg":"","hidden_xl":"","hidden_md":"","hidden_sm":"","hidden_xs":"","style":"JAxhtml","extra_class":"","extra_params":"","modname":"mod_breadcrumbs","title":"Breadcrumbs","module":"","positions":"footnav-2","block":"","element":"","device":"def","idx":1},{"type":"positions","name":"footnav-3","col":2,"xl":"","lg":3,"md":3,"sm":6,"xs":12,"hidden_lg":"","hidden_xl":"","hidden_md":"","hidden_sm":"","hidden_xs":"","style":"JAxhtml","extra_class":"","extra_params":"","modname":"mod_breadcrumbs","title":"Breadcrumbs","module":"","positions":"footnav-3","block":"","element":"","device":"def","idx":2},{"type":"positions","name":"footnav-4","col":2,"xl":"","lg":3,"md":3,"sm":6,"xs":12,"hidden_lg":"","hidden_xl":"","hidden_md":"","hidden_sm":"","hidden_xs":"","style":"JAxhtml","extra_class":"","extra_params":"","modname":"mod_breadcrumbs","title":"Breadcrumbs","module":"","positions":"footnav-4","block":"","element":"","device":"def","idx":3},{"type":"positions","name":"footnav-5","col":2,"xl":"","lg":3,"md":3,"sm":6,"xs":"","hidden_lg":"","hidden_xl":"","hidden_md":"","hidden_sm":"","hidden_xs":"","style":"JAxhtml","extra_class":"","extra_params":"","element":null,"block":null,"positions":"footnav-5","module":null,"device":"def","idx":4}],"opacity":0.5,"file_ogg":"","file_webm":"","file_mp4":"","file_cover":"","video_id":"","video_type":null,"background_position":"50% 0","background_attachment":"inherit","background_size":"auto","background_repeat":"no-repeat","background_image":"","overlay_type":"image","color_pattern":"","sticky":"","extra_class":"","margin":"","padding":"","cols":5,"container":"","name":"Footnav","margin_xs":"","margin_sm":"","margin_md":"","margin_lg":"","margin_xl":"","padding_xs":"","padding_sm":"","padding_md":"","padding_lg":"","padding_xl":"","type":"row","layout":"4+2+2+2+2","sectionid":1},{"contents":[{"type":"positions","name":"copyright","col":"auto","xl":"","lg":"","md":"","sm":"","xs":"","hidden_lg":"","hidden_xl":"","hidden_md":"","hidden_sm":"","hidden_xs":"","style":null,"extra_class":"","extra_params":"","element":null,"block":null,"positions":"copyright","module":null,"device":"def","title":"Breadcrumbs","modname":"mod_breadcrumbs","idx":0}],"margin_xs":"","margin_sm":"","margin_md":"","margin_lg":"","margin_xl":"","padding_xs":"","padding_sm":"","padding_md":"","padding_lg":"","padding_xl":"","type":"row","layout":"auto","name":"Copyright","container":1,"cols":2,"padding":"","margin":"","extra_class":" section-border-top","sticky":"","color_pattern":"","overlay_type":"","background_image":"","background_repeat":null,"background_size":null,"background_attachment":null,"background_position":null,"video_type":null,"video_id":"","file_cover":"","file_mp4":"","file_webm":"","file_ogg":"","opacity":0.5}],"settings":{"assets":[],"fonts":[]}}}